pipeline_sdk_test73/__init__.py
pipeline_sdk_test73/auth_service.py
pipeline_sdk_test73/inference_pipeline.py
pipeline_sdk_test73/model_inference_dsl_component.py
pipeline_sdk_test73/model_train_dsl_component.py
pipeline_sdk_test73/model_validate_dsl_component.py
pipeline_sdk_test73/pipeline_util.py
pipeline_sdk_test73/run_inference_pipeline.py
pipeline_sdk_test73/run_training_pipeline.py
pipeline_sdk_test73/run_validate_pipeline.py
pipeline_sdk_test73/train_pipeline.py
pipeline_sdk_test73/validate_pipeline.py
pipeline_sdk_test73-1.0.0.dist-info/METADATA
pipeline_sdk_test73-1.0.0.dist-info/WHEEL
pipeline_sdk_test73-1.0.0.dist-info/top_level.txt
pipeline_sdk_test73-1.0.0.dist-info/RECORD
